vectorim/__init__.py
vectorim/vectorim.py
vectorim-0.0.1.dist-info/LICENSE
vectorim-0.0.1.dist-info/METADATA
vectorim-0.0.1.dist-info/WHEEL
vectorim-0.0.1.dist-info/top_level.txt
vectorim-0.0.1.dist-info/RECORD
