Metadata-Version: 2.1
Name: vectorim
Version: 0.0.1
Summary: A simple, no bs vector database for experimentation and prototyping
Author-email: Ariel Schoen <ariel@shape-ai.com>
Project-URL: Homepage, https://github.com/in-shape/vectorim
Classifier: Programming Language :: Python :: 3
Classifier: License :: OSI Approved :: MIT License
Classifier: Operating System :: OS Independent
Requires-Python: >=3.7
License-File: LICENSE
Requires-Dist: numpy
